netcdf_unpacker/__init__.py
netcdf_unpacker/netcdf_unpacker.py
netcdf_unpacker-1.1.dist-info/LICENSE
netcdf_unpacker-1.1.dist-info/METADATA
netcdf_unpacker-1.1.dist-info/WHEEL
netcdf_unpacker-1.1.dist-info/top_level.txt
netcdf_unpacker-1.1.dist-info/RECORD
